odoo/addons/account_bank_statement_import_split/README.rst
odoo/addons/account_bank_statement_import_split/__init__.py
odoo/addons/account_bank_statement_import_split/__manifest__.py
odoo/addons/account_bank_statement_import_split/i18n/account_bank_statement_import_split.pot
odoo/addons/account_bank_statement_import_split/models/__init__.py
odoo/addons/account_bank_statement_import_split/models/account_bank_statement_import.py
odoo/addons/account_bank_statement_import_split/readme/CONTRIBUTORS.rst
odoo/addons/account_bank_statement_import_split/readme/DESCRIPTION.rst
odoo/addons/account_bank_statement_import_split/static/description/icon.png
odoo/addons/account_bank_statement_import_split/static/description/index.html
odoo/addons/account_bank_statement_import_split/tests/__init__.py
odoo/addons/account_bank_statement_import_split/tests/test_account_bank_statement_import_split.py
odoo/addons/account_bank_statement_import_split/views/account_bank_statement_import.xml
odoo13_addon_account_bank_statement_import_split-13.0.1.0.1.dev3.dist-info/METADATA
odoo13_addon_account_bank_statement_import_split-13.0.1.0.1.dev3.dist-info/WHEEL
odoo13_addon_account_bank_statement_import_split-13.0.1.0.1.dev3.dist-info/top_level.txt
odoo13_addon_account_bank_statement_import_split-13.0.1.0.1.dev3.dist-info/RECORD
